[
  {"floor": 9, "seat": 1, "area": "a", "username": "nitardor" },
  {"floor": 9, "seat": 2, "area": "a", "username": "almeich" },
  {"floor": 9, "seat": 3, "area": "a", "username": "almeich" },
  {"floor": 9, "seat": 5, "area": "a", "username": "almeich" },
  {"floor": 9, "seat": 17, "area": "b", "username": "almeich" },
  {"floor": 9, "seat": 7, "area": "c", "username": "almeich" },
  {"floor": 9, "seat": 8, "area": "c", "username": "almeich" },
  {"floor": 9, "seat": 11, "area": "c", "username": "almeich" },
  {"floor": 9, "seat": 12, "area": "c", "username": "almeich" },
  {"floor": 9, "seat": 14, "area": "c", "username": "almeich" },
  {"floor": 9, "seat": 16, "area": "c", "username": "almeich" },
  {"floor": 14, "seat": 146, "area": "b1", "username": "justij" },
  {"floor": 14, "seat": 148, "area": "b1", "username": "justij" },
  {"floor": 14, "seat": 150, "area": "b1", "username": "justij" },
  {"floor": 15, "seat": 133, "area": "b1", "username": "ferree2" },
  {"floor": 15, "seat": 134, "area": "b1", "username": "ribeia8" },
  {"floor": 15, "seat": 136, "area": "b1", "username": "oliveb3" },
  {"floor": 15, "seat": 151, "area": "b1", "username": "nevesdpr" },
  {"floor": 15, "seat": 157, "area": "b1", "username": "thimotc" },
  {"floor": 15, "seat": 161, "area": "b1", "username": "santoaw" },
  {"floor": 15, "seat": 201, "area": "b1", "username": "ferreaw" },
  {"floor": 16, "seat": 67, "area": "c1", "username": "escarima" },
  {"floor": 16, "seat": 69, "area": "c1", "username": "escarima" },
  {"floor": 16, "seat": 72, "area": "c1", "username": "escarima" },
  {"floor": 16, "seat": 73, "area": "c1", "username": "amatop5" },
  {"floor": 16, "seat": 74, "area": "c1", "username": "dasilvim" },
  {"floor": 16, "seat": 76, "area": "c1", "username": "pereirjr" },
  {"floor": 16, "seat": 79, "area": "c1", "username": "mendesmu" },
  {"floor": 16, "seat": 81, "area": "c1", "username": "scurzir" },
  {"floor": 16, "seat": 82, "area": "b2", "username": "costaef" },
  {"floor": 16, "seat": 84, "area": "b2", "username": "costaef" },
  {"floor": 16, "seat": 206, "area": "b2", "username": "costaef" },
  {"floor": 16, "seat": 116, "area": "b2", "username": "xavierf" },
  {"floor": 16, "seat": 118, "area": "b2", "username": "riccojn" },
  {"floor": 16, "seat": 120, "area": "b2", "username": "goncaljr" },
  {"floor": 16, "seat": 122, "area": "b2", "username": "goncaljr" },
  {"floor": 16, "seat": 112, "area": "b1", "username": "diassae" },
  {"floor": 16, "seat": 115, "area": "b1", "username": "carreic" },
  {"floor": 17, "seat": 28, "area": "b2", "username": "beilse" }
]