[
  {
    "Site_name": "Costa Rica",
    "New_Site_name": "San Rafael de Escazu, San José",
    "Site_BM": "2cc5f62b-5b1e-4aac-b6b0-5b98f724927f",
    "Bldg_name": "EPIC",
    "New_Bldg_name": "Oficentro Comercial EPIC",
    "Bldg_BM": "649d3662-2705-4302-91ba-b492750bf5a0",
    "Floor_number": 1,
    "New_Floor_number": 0,
    "Floor_BM": "fb81710b-b101-4270-8d65-98158eb2af40",
    "Area_Code": "A",
    "New_Area_Code": "-",
    "Area_BM": "fb81710b-b101-4270-8d65-98158eb2af40",
    "Seat_ID": 6311,
    "Seat_Code": 1,
    "New_Seat_Code": "1-01",
    "Seat_BM": "e8229cc1-d9bd-48e3-9a56-e41c63fda611"
  },
  {
    "Site_name": "Costa Rica",
    "New_Site_name": "San Rafael de Escazu, San José",
    "Site_BM": "2cc5f62b-5b1e-4aac-b6b0-5b98f724927f",
    "Bldg_name": "EPIC",
    "New_Bldg_name": "Oficentro Comercial EPIC",
    "Bldg_BM": "649d3662-2705-4302-91ba-b492750bf5a0",
    "Floor_number": 1,
    "New_Floor_number": 0,
    "Floor_BM": "fb81710b-b101-4270-8d65-98158eb2af40",
    "Area_Code": "A",
    "New_Area_Code": "-",
    "Area_BM": "fb81710b-b101-4270-8d65-98158eb2af40",
    "Seat_ID": 6312,
    "Seat_Code": 2,
    "New_Seat_Code": "1-02",
    "Seat_BM": "78ea9af7-7384-4393-a10a-8af5d5866459"
  },
  {
    "Site_name": "Costa Rica",
    "New_Site_name": "San Rafael de Escazu, San José",
    "Site_BM": "2cc5f62b-5b1e-4aac-b6b0-5b98f724927f",
    "Bldg_name": "EPIC",
    "New_Bldg_name": "Oficentro Comercial EPIC",
    "Bldg_BM": "649d3662-2705-4302-91ba-b492750bf5a0",
    "Floor_number": 1,
    "New_Floor_number": 0,
    "Floor_BM": "fb81710b-b101-4270-8d65-98158eb2af40",
    "Area_Code": "A",
    "New_Area_Code": "-",
    "Area_BM": "fb81710b-b101-4270-8d65-98158eb2af40",
    "Seat_ID": 6313,
    "Seat_Code": 3,
    "New_Seat_Code": "1-03",
    "Seat_BM": "038ed19c-055c-464d-b2ef-fa66c5cb1dcc"
  },
  {
    "Site_name": "Costa Rica",
    "New_Site_name": "San Rafael de Escazu, San José",
    "Site_BM": "2cc5f62b-5b1e-4aac-b6b0-5b98f724927f",
    "Bldg_name": "EPIC",
    "New_Bldg_name": "Oficentro Comercial EPIC",
    "Bldg_BM": "649d3662-2705-4302-91ba-b492750bf5a0",
    "Floor_number": 1,
    "New_Floor_number": 0,
    "Floor_BM": "fb81710b-b101-4270-8d65-98158eb2af40",
    "Area_Code": "A",
    "New_Area_Code": "-",
    "Area_BM": "fb81710b-b101-4270-8d65-98158eb2af40",
    "Seat_ID": 6314,
    "Seat_Code": 4,
    "New_Seat_Code": "1-04",
    "Seat_BM": "1e1c23fd-04b3-4da0-82dd-24dcdb9241b9"
  },
  {
    "Site_name": "Costa Rica",
    "New_Site_name": "San Rafael de Escazu, San José",
    "Site_BM": "2cc5f62b-5b1e-4aac-b6b0-5b98f724927f",
    "Bldg_name": "EPIC",
    "New_Bldg_name": "Oficentro Comercial EPIC",
    "Bldg_BM": "649d3662-2705-4302-91ba-b492750bf5a0",
    "Floor_number": 1,
    "New_Floor_number": 0,
    "Floor_BM": "fb81710b-b101-4270-8d65-98158eb2af40",
    "Area_Code": "A",
    "New_Area_Code": "-",
    "Area_BM": "fb81710b-b101-4270-8d65-98158eb2af40",
    "Seat_ID": 6315,
    "Seat_Code": 5,
    "New_Seat_Code": "1-05",
    "Seat_BM": "f14dc3d9-dad6-4922-b6c5-267ce930e4a5"
  },
  {
    "Site_name": "Costa Rica",
    "New_Site_name": "San Rafael de Escazu, San José",
    "Site_BM": "2cc5f62b-5b1e-4aac-b6b0-5b98f724927f",
    "Bldg_name": "EPIC",
    "New_Bldg_name": "Oficentro Comercial EPIC",
    "Bldg_BM": "649d3662-2705-4302-91ba-b492750bf5a0",
    "Floor_number": 1,
    "New_Floor_number": 0,
    "Floor_BM": "fb81710b-b101-4270-8d65-98158eb2af40",
    "Area_Code": "A",
    "New_Area_Code": "-",
    "Area_BM": "fb81710b-b101-4270-8d65-98158eb2af40",
    "Seat_ID": 6316,
    "Seat_Code": 6,
    "New_Seat_Code": "1-06",
    "Seat_BM": "d7ff8d79-4b27-41de-ada4-cd1720108baf"
  },
  {
    "Site_name": "Costa Rica",
    "New_Site_name": "San Rafael de Escazu, San José",
    "Site_BM": "2cc5f62b-5b1e-4aac-b6b0-5b98f724927f",
    "Bldg_name": "EPIC",
    "New_Bldg_name": "Oficentro Comercial EPIC",
    "Bldg_BM": "649d3662-2705-4302-91ba-b492750bf5a0",
    "Floor_number": 1,
    "New_Floor_number": 0,
    "Floor_BM": "fb81710b-b101-4270-8d65-98158eb2af40",
    "Area_Code": "A",
    "New_Area_Code": "-",
    "Area_BM": "fb81710b-b101-4270-8d65-98158eb2af40",
    "Seat_ID": 6317,
    "Seat_Code": 7,
    "New_Seat_Code": "1-07",
    "Seat_BM": "970aa777-9091-4d29-af65-878f8b970a83"
  },
  {
    "Site_name": "Costa Rica",
    "New_Site_name": "San Rafael de Escazu, San José",
    "Site_BM": "2cc5f62b-5b1e-4aac-b6b0-5b98f724927f",
    "Bldg_name": "EPIC",
    "New_Bldg_name": "Oficentro Comercial EPIC",
    "Bldg_BM": "649d3662-2705-4302-91ba-b492750bf5a0",
    "Floor_number": 1,
    "New_Floor_number": 0,
    "Floor_BM": "fb81710b-b101-4270-8d65-98158eb2af40",
    "Area_Code": "A",
    "New_Area_Code": "-",
    "Area_BM": "fb81710b-b101-4270-8d65-98158eb2af40",
    "Seat_ID": 6318,
    "Seat_Code": 8,
    "New_Seat_Code": "1-08",
    "Seat_BM": "daa8ebdf-c1a2-4d39-9b70-0145c3f69d18"
  },
  {
    "Site_name": "Costa Rica",
    "New_Site_name": "San Rafael de Escazu, San José",
    "Site_BM": "2cc5f62b-5b1e-4aac-b6b0-5b98f724927f",
    "Bldg_name": "EPIC",
    "New_Bldg_name": "Oficentro Comercial EPIC",
    "Bldg_BM": "649d3662-2705-4302-91ba-b492750bf5a0",
    "Floor_number": 1,
    "New_Floor_number": 0,
    "Floor_BM": "fb81710b-b101-4270-8d65-98158eb2af40",
    "Area_Code": "A",
    "New_Area_Code": "-",
    "Area_BM": "fb81710b-b101-4270-8d65-98158eb2af40",
    "Seat_ID": 6319,
    "Seat_Code": 9,
    "New_Seat_Code": "1-09",
    "Seat_BM": "f52010e4-2f05-436e-bd46-c2e782be0e44"
  },
  {
    "Site_name": "Costa Rica",
    "New_Site_name": "San Rafael de Escazu, San José",
    "Site_BM": "2cc5f62b-5b1e-4aac-b6b0-5b98f724927f",
    "Bldg_name": "EPIC",
    "New_Bldg_name": "Oficentro Comercial EPIC",
    "Bldg_BM": "649d3662-2705-4302-91ba-b492750bf5a0",
    "Floor_number": 1,
    "New_Floor_number": 0,
    "Floor_BM": "fb81710b-b101-4270-8d65-98158eb2af40",
    "Area_Code": "A",
    "New_Area_Code": "-",
    "Area_BM": "fb81710b-b101-4270-8d65-98158eb2af40",
    "Seat_ID": 6320,
    "Seat_Code": 10,
    "New_Seat_Code": "1-10",
    "Seat_BM": "f84eb8f2-72e8-42f6-82f7-480c5049c2ce"
  },
  {
    "Site_name": "Costa Rica",
    "New_Site_name": "San Rafael de Escazu, San José",
    "Site_BM": "2cc5f62b-5b1e-4aac-b6b0-5b98f724927f",
    "Bldg_name": "EPIC",
    "New_Bldg_name": "Oficentro Comercial EPIC",
    "Bldg_BM": "649d3662-2705-4302-91ba-b492750bf5a0",
    "Floor_number": 1,
    "New_Floor_number": 0,
    "Floor_BM": "fb81710b-b101-4270-8d65-98158eb2af40",
    "Area_Code": "A",
    "New_Area_Code": "-",
    "Area_BM": "fb81710b-b101-4270-8d65-98158eb2af40",
    "Seat_ID": 6321,
    "Seat_Code": 11,
    "New_Seat_Code": "1-11",
    "Seat_BM": "d139d1d2-8678-40d0-8557-0af6fba51dbb"
  },
  {
    "Site_name": "Costa Rica",
    "New_Site_name": "San Rafael de Escazu, San José",
    "Site_BM": "2cc5f62b-5b1e-4aac-b6b0-5b98f724927f",
    "Bldg_name": "EPIC",
    "New_Bldg_name": "Oficentro Comercial EPIC",
    "Bldg_BM": "649d3662-2705-4302-91ba-b492750bf5a0",
    "Floor_number": 1,
    "New_Floor_number": 0,
    "Floor_BM": "fb81710b-b101-4270-8d65-98158eb2af40",
    "Area_Code": "A",
    "New_Area_Code": "-",
    "Area_BM": "fb81710b-b101-4270-8d65-98158eb2af40",
    "Seat_ID": 6322,
    "Seat_Code": 12,
    "New_Seat_Code": "1-12",
    "Seat_BM": "c4da4088-3b60-47c8-a912-7cc746def7f2"
  },
  {
    "Site_name": "Costa Rica",
    "New_Site_name": "San Rafael de Escazu, San José",
    "Site_BM": "2cc5f62b-5b1e-4aac-b6b0-5b98f724927f",
    "Bldg_name": "EPIC",
    "New_Bldg_name": "Oficentro Comercial EPIC",
    "Bldg_BM": "649d3662-2705-4302-91ba-b492750bf5a0",
    "Floor_number": 1,
    "New_Floor_number": 0,
    "Floor_BM": "fb81710b-b101-4270-8d65-98158eb2af40",
    "Area_Code": "A",
    "New_Area_Code": "-",
    "Area_BM": "fb81710b-b101-4270-8d65-98158eb2af40",
    "Seat_ID": 6323,
    "Seat_Code": 13,
    "New_Seat_Code": "1-13",
    "Seat_BM": "7e46d1b7-bbfe-41c4-bb1f-487c1591eb22"
  },
  {
    "Site_name": "Costa Rica",
    "New_Site_name": "San Rafael de Escazu, San José",
    "Site_BM": "2cc5f62b-5b1e-4aac-b6b0-5b98f724927f",
    "Bldg_name": "EPIC",
    "New_Bldg_name": "Oficentro Comercial EPIC",
    "Bldg_BM": "649d3662-2705-4302-91ba-b492750bf5a0",
    "Floor_number": 1,
    "New_Floor_number": 0,
    "Floor_BM": "fb81710b-b101-4270-8d65-98158eb2af40",
    "Area_Code": "A",
    "New_Area_Code": "-",
    "Area_BM": "fb81710b-b101-4270-8d65-98158eb2af40",
    "Seat_ID": 6324,
    "Seat_Code": 14,
    "New_Seat_Code": "1-14",
    "Seat_BM": "69c60f51-e874-4317-929b-4a9a38305f43"
  },
  {
    "Site_name": "Costa Rica",
    "New_Site_name": "San Rafael de Escazu, San José",
    "Site_BM": "2cc5f62b-5b1e-4aac-b6b0-5b98f724927f",
    "Bldg_name": "EPIC",
    "New_Bldg_name": "Oficentro Comercial EPIC",
    "Bldg_BM": "649d3662-2705-4302-91ba-b492750bf5a0",
    "Floor_number": 1,
    "New_Floor_number": 0,
    "Floor_BM": "fb81710b-b101-4270-8d65-98158eb2af40",
    "Area_Code": "A",
    "New_Area_Code": "-",
    "Area_BM": "fb81710b-b101-4270-8d65-98158eb2af40",
    "Seat_ID": 6325,
    "Seat_Code": 15,
    "New_Seat_Code": "1-15",
    "Seat_BM": "f9976610-af23-46e6-a7f0-e0d2edabfe38"
  },
  {
    "Site_name": "Costa Rica",
    "New_Site_name": "San Rafael de Escazu, San José",
    "Site_BM": "2cc5f62b-5b1e-4aac-b6b0-5b98f724927f",
    "Bldg_name": "EPIC",
    "New_Bldg_name": "Oficentro Comercial EPIC",
    "Bldg_BM": "649d3662-2705-4302-91ba-b492750bf5a0",
    "Floor_number": 1,
    "New_Floor_number": 0,
    "Floor_BM": "fb81710b-b101-4270-8d65-98158eb2af40",
    "Area_Code": "A",
    "New_Area_Code": "-",
    "Area_BM": "fb81710b-b101-4270-8d65-98158eb2af40",
    "Seat_ID": 6326,
    "Seat_Code": 16,
    "New_Seat_Code": "1-16",
    "Seat_BM": "775942a7-3673-4c11-9f66-abd65dba25ee"
  },
  {
    "Site_name": "Costa Rica",
    "New_Site_name": "San Rafael de Escazu, San José",
    "Site_BM": "2cc5f62b-5b1e-4aac-b6b0-5b98f724927f",
    "Bldg_name": "EPIC",
    "New_Bldg_name": "Oficentro Comercial EPIC",
    "Bldg_BM": "649d3662-2705-4302-91ba-b492750bf5a0",
    "Floor_number": 1,
    "New_Floor_number": 0,
    "Floor_BM": "fb81710b-b101-4270-8d65-98158eb2af40",
    "Area_Code": "A",
    "New_Area_Code": "-",
    "Area_BM": "fb81710b-b101-4270-8d65-98158eb2af40",
    "Seat_ID": 6327,
    "Seat_Code": 17,
    "New_Seat_Code": "1-17",
    "Seat_BM": "ab8a6a16-81be-4f99-b380-3e927b878e72"
  },
  {
    "Site_name": "Costa Rica",
    "New_Site_name": "San Rafael de Escazu, San José",
    "Site_BM": "2cc5f62b-5b1e-4aac-b6b0-5b98f724927f",
    "Bldg_name": "EPIC",
    "New_Bldg_name": "Oficentro Comercial EPIC",
    "Bldg_BM": "649d3662-2705-4302-91ba-b492750bf5a0",
    "Floor_number": 1,
    "New_Floor_number": 0,
    "Floor_BM": "fb81710b-b101-4270-8d65-98158eb2af40",
    "Area_Code": "A",
    "New_Area_Code": "-",
    "Area_BM": "fb81710b-b101-4270-8d65-98158eb2af40",
    "Seat_ID": 6328,
    "Seat_Code": 18,
    "New_Seat_Code": "1-18",
    "Seat_BM": "a0c9d369-d732-472e-99f1-021033b9f8a7"
  },
  {
    "Site_name": "Costa Rica",
    "New_Site_name": "San Rafael de Escazu, San José",
    "Site_BM": "2cc5f62b-5b1e-4aac-b6b0-5b98f724927f",
    "Bldg_name": "EPIC",
    "New_Bldg_name": "Oficentro Comercial EPIC",
    "Bldg_BM": "649d3662-2705-4302-91ba-b492750bf5a0",
    "Floor_number": 1,
    "New_Floor_number": 0,
    "Floor_BM": "fb81710b-b101-4270-8d65-98158eb2af40",
    "Area_Code": "A",
    "New_Area_Code": "-",
    "Area_BM": "fb81710b-b101-4270-8d65-98158eb2af40",
    "Seat_ID": 6329,
    "Seat_Code": 19,
    "New_Seat_Code": "1-19",
    "Seat_BM": "d56ab775-fd9c-4b5c-bfe7-9651de9206b8"
  },
  {
    "Site_name": "Costa Rica",
    "New_Site_name": "San Rafael de Escazu, San José",
    "Site_BM": "2cc5f62b-5b1e-4aac-b6b0-5b98f724927f",
    "Bldg_name": "EPIC",
    "New_Bldg_name": "Oficentro Comercial EPIC",
    "Bldg_BM": "649d3662-2705-4302-91ba-b492750bf5a0",
    "Floor_number": 1,
    "New_Floor_number": 0,
    "Floor_BM": "fb81710b-b101-4270-8d65-98158eb2af40",
    "Area_Code": "A",
    "New_Area_Code": "-",
    "Area_BM": "fb81710b-b101-4270-8d65-98158eb2af40",
    "Seat_ID": 6330,
    "Seat_Code": 20,
    "New_Seat_Code": "1-20",
    "Seat_BM": "34274684-09fb-4db5-88a7-10c75510d142"
  },
  {
    "Site_name": "Costa Rica",
    "New_Site_name": "San Rafael de Escazu, San José",
    "Site_BM": "2cc5f62b-5b1e-4aac-b6b0-5b98f724927f",
    "Bldg_name": "EPIC",
    "New_Bldg_name": "Oficentro Comercial EPIC",
    "Bldg_BM": "649d3662-2705-4302-91ba-b492750bf5a0",
    "Floor_number": 1,
    "New_Floor_number": 0,
    "Floor_BM": "fb81710b-b101-4270-8d65-98158eb2af40",
    "Area_Code": "A",
    "New_Area_Code": "-",
    "Area_BM": "fb81710b-b101-4270-8d65-98158eb2af40",
    "Seat_ID": 6331,
    "Seat_Code": 21,
    "New_Seat_Code": "1-21",
    "Seat_BM": "20f484b3-4982-43f8-bccf-2e311b5ce12b"
  },
  {
    "Site_name": "Costa Rica",
    "New_Site_name": "San Rafael de Escazu, San José",
    "Site_BM": "2cc5f62b-5b1e-4aac-b6b0-5b98f724927f",
    "Bldg_name": "EPIC",
    "New_Bldg_name": "Oficentro Comercial EPIC",
    "Bldg_BM": "649d3662-2705-4302-91ba-b492750bf5a0",
    "Floor_number": 1,
    "New_Floor_number": 0,
    "Floor_BM": "fb81710b-b101-4270-8d65-98158eb2af40",
    "Area_Code": "A",
    "New_Area_Code": "-",
    "Area_BM": "fb81710b-b101-4270-8d65-98158eb2af40",
    "Seat_ID": 6332,
    "Seat_Code": 22,
    "New_Seat_Code": "1-22",
    "Seat_BM": "ed7fa1f2-d7f2-48aa-b1ec-99a1b1d9e494"
  },
  {
    "Site_name": "Costa Rica",
    "New_Site_name": "San Rafael de Escazu, San José",
    "Site_BM": "2cc5f62b-5b1e-4aac-b6b0-5b98f724927f",
    "Bldg_name": "EPIC",
    "New_Bldg_name": "Oficentro Comercial EPIC",
    "Bldg_BM": "649d3662-2705-4302-91ba-b492750bf5a0",
    "Floor_number": 1,
    "New_Floor_number": 0,
    "Floor_BM": "fb81710b-b101-4270-8d65-98158eb2af40",
    "Area_Code": "B",
    "New_Area_Code": "-",
    "Area_BM": "fb81710b-b101-4270-8d65-98158eb2af40",
    "Seat_ID": 6333,
    "Seat_Code": 1,
    "New_Seat_Code": "2-01",
    "Seat_BM": "87ea3679-66cf-4cf5-b2c7-f5fb4394537f"
  },
  {
    "Site_name": "Costa Rica",
    "New_Site_name": "San Rafael de Escazu, San José",
    "Site_BM": "2cc5f62b-5b1e-4aac-b6b0-5b98f724927f",
    "Bldg_name": "EPIC",
    "New_Bldg_name": "Oficentro Comercial EPIC",
    "Bldg_BM": "649d3662-2705-4302-91ba-b492750bf5a0",
    "Floor_number": 1,
    "New_Floor_number": 0,
    "Floor_BM": "fb81710b-b101-4270-8d65-98158eb2af40",
    "Area_Code": "B",
    "New_Area_Code": "-",
    "Area_BM": "fb81710b-b101-4270-8d65-98158eb2af40",
    "Seat_ID": 6334,
    "Seat_Code": 2,
    "New_Seat_Code": "2-02",
    "Seat_BM": "ee720cb1-6ca3-4f26-9407-2a3207bf6c9b"
  },
  {
    "Site_name": "Costa Rica",
    "New_Site_name": "San Rafael de Escazu, San José",
    "Site_BM": "2cc5f62b-5b1e-4aac-b6b0-5b98f724927f",
    "Bldg_name": "EPIC",
    "New_Bldg_name": "Oficentro Comercial EPIC",
    "Bldg_BM": "649d3662-2705-4302-91ba-b492750bf5a0",
    "Floor_number": 1,
    "New_Floor_number": 0,
    "Floor_BM": "fb81710b-b101-4270-8d65-98158eb2af40",
    "Area_Code": "B",
    "New_Area_Code": "-",
    "Area_BM": "fb81710b-b101-4270-8d65-98158eb2af40",
    "Seat_ID": 6335,
    "Seat_Code": 3,
    "New_Seat_Code": "2-03",
    "Seat_BM": "e7bc2efb-c213-4742-a357-227214215e9a"
  },
  {
    "Site_name": "Costa Rica",
    "New_Site_name": "San Rafael de Escazu, San José",
    "Site_BM": "2cc5f62b-5b1e-4aac-b6b0-5b98f724927f",
    "Bldg_name": "EPIC",
    "New_Bldg_name": "Oficentro Comercial EPIC",
    "Bldg_BM": "649d3662-2705-4302-91ba-b492750bf5a0",
    "Floor_number": 1,
    "New_Floor_number": 0,
    "Floor_BM": "fb81710b-b101-4270-8d65-98158eb2af40",
    "Area_Code": "B",
    "New_Area_Code": "-",
    "Area_BM": "fb81710b-b101-4270-8d65-98158eb2af40",
    "Seat_ID": 6336,
    "Seat_Code": 4,
    "New_Seat_Code": "2-04",
    "Seat_BM": "62759607-101d-4703-a487-9dcd314e3eee"
  },
  {
    "Site_name": "Costa Rica",
    "New_Site_name": "San Rafael de Escazu, San José",
    "Site_BM": "2cc5f62b-5b1e-4aac-b6b0-5b98f724927f",
    "Bldg_name": "EPIC",
    "New_Bldg_name": "Oficentro Comercial EPIC",
    "Bldg_BM": "649d3662-2705-4302-91ba-b492750bf5a0",
    "Floor_number": 1,
    "New_Floor_number": 0,
    "Floor_BM": "fb81710b-b101-4270-8d65-98158eb2af40",
    "Area_Code": "B",
    "New_Area_Code": "-",
    "Area_BM": "fb81710b-b101-4270-8d65-98158eb2af40",
    "Seat_ID": 6337,
    "Seat_Code": 5,
    "New_Seat_Code": "2-05",
    "Seat_BM": "2788c55b-c369-4607-9f1d-c15cb7240ea6"
  },
  {
    "Site_name": "Costa Rica",
    "New_Site_name": "San Rafael de Escazu, San José",
    "Site_BM": "2cc5f62b-5b1e-4aac-b6b0-5b98f724927f",
    "Bldg_name": "EPIC",
    "New_Bldg_name": "Oficentro Comercial EPIC",
    "Bldg_BM": "649d3662-2705-4302-91ba-b492750bf5a0",
    "Floor_number": 1,
    "New_Floor_number": 0,
    "Floor_BM": "fb81710b-b101-4270-8d65-98158eb2af40",
    "Area_Code": "B",
    "New_Area_Code": "-",
    "Area_BM": "fb81710b-b101-4270-8d65-98158eb2af40",
    "Seat_ID": 6338,
    "Seat_Code": 6,
    "New_Seat_Code": "2-06",
    "Seat_BM": "03951483-9ccf-4540-82c5-e254a0572ef0"
  },
  {
    "Site_name": "Costa Rica",
    "New_Site_name": "San Rafael de Escazu, San José",
    "Site_BM": "2cc5f62b-5b1e-4aac-b6b0-5b98f724927f",
    "Bldg_name": "EPIC",
    "New_Bldg_name": "Oficentro Comercial EPIC",
    "Bldg_BM": "649d3662-2705-4302-91ba-b492750bf5a0",
    "Floor_number": 1,
    "New_Floor_number": 0,
    "Floor_BM": "fb81710b-b101-4270-8d65-98158eb2af40",
    "Area_Code": "B",
    "New_Area_Code": "-",
    "Area_BM": "fb81710b-b101-4270-8d65-98158eb2af40",
    "Seat_ID": 6339,
    "Seat_Code": 7,
    "New_Seat_Code": "2-07",
    "Seat_BM": "68508348-3671-4edc-b4fd-29222be62f33"
  },
  {
    "Site_name": "Costa Rica",
    "New_Site_name": "San Rafael de Escazu, San José",
    "Site_BM": "2cc5f62b-5b1e-4aac-b6b0-5b98f724927f",
    "Bldg_name": "EPIC",
    "New_Bldg_name": "Oficentro Comercial EPIC",
    "Bldg_BM": "649d3662-2705-4302-91ba-b492750bf5a0",
    "Floor_number": 1,
    "New_Floor_number": 0,
    "Floor_BM": "fb81710b-b101-4270-8d65-98158eb2af40",
    "Area_Code": "B",
    "New_Area_Code": "-",
    "Area_BM": "fb81710b-b101-4270-8d65-98158eb2af40",
    "Seat_ID": 6340,
    "Seat_Code": 8,
    "New_Seat_Code": "2-08",
    "Seat_BM": "35a8e789-99a5-4956-a4b7-89da111120d5"
  },
  {
    "Site_name": "Costa Rica",
    "New_Site_name": "San Rafael de Escazu, San José",
    "Site_BM": "2cc5f62b-5b1e-4aac-b6b0-5b98f724927f",
    "Bldg_name": "EPIC",
    "New_Bldg_name": "Oficentro Comercial EPIC",
    "Bldg_BM": "649d3662-2705-4302-91ba-b492750bf5a0",
    "Floor_number": 1,
    "New_Floor_number": 0,
    "Floor_BM": "fb81710b-b101-4270-8d65-98158eb2af40",
    "Area_Code": "B",
    "New_Area_Code": "-",
    "Area_BM": "fb81710b-b101-4270-8d65-98158eb2af40",
    "Seat_ID": 6341,
    "Seat_Code": 9,
    "New_Seat_Code": "2-09",
    "Seat_BM": "564d058a-960f-4c01-929f-a6c31b2dc4d3"
  },
  {
    "Site_name": "Costa Rica",
    "New_Site_name": "San Rafael de Escazu, San José",
    "Site_BM": "2cc5f62b-5b1e-4aac-b6b0-5b98f724927f",
    "Bldg_name": "EPIC",
    "New_Bldg_name": "Oficentro Comercial EPIC",
    "Bldg_BM": "649d3662-2705-4302-91ba-b492750bf5a0",
    "Floor_number": 1,
    "New_Floor_number": 0,
    "Floor_BM": "fb81710b-b101-4270-8d65-98158eb2af40",
    "Area_Code": "B",
    "New_Area_Code": "-",
    "Area_BM": "fb81710b-b101-4270-8d65-98158eb2af40",
    "Seat_ID": 6342,
    "Seat_Code": 10,
    "New_Seat_Code": "2-10",
    "Seat_BM": "726faedd-ca8a-473d-ba2d-c142082c3fc2"
  },
  {
    "Site_name": "Costa Rica",
    "New_Site_name": "San Rafael de Escazu, San José",
    "Site_BM": "2cc5f62b-5b1e-4aac-b6b0-5b98f724927f",
    "Bldg_name": "EPIC",
    "New_Bldg_name": "Oficentro Comercial EPIC",
    "Bldg_BM": "649d3662-2705-4302-91ba-b492750bf5a0",
    "Floor_number": 1,
    "New_Floor_number": 0,
    "Floor_BM": "fb81710b-b101-4270-8d65-98158eb2af40",
    "Area_Code": "B",
    "New_Area_Code": "-",
    "Area_BM": "fb81710b-b101-4270-8d65-98158eb2af40",
    "Seat_ID": 6343,
    "Seat_Code": 11,
    "New_Seat_Code": "2-11",
    "Seat_BM": "bec53fd9-d645-4d6d-8d95-59c2656f8c65"
  },
  {
    "Site_name": "Costa Rica",
    "New_Site_name": "San Rafael de Escazu, San José",
    "Site_BM": "2cc5f62b-5b1e-4aac-b6b0-5b98f724927f",
    "Bldg_name": "EPIC",
    "New_Bldg_name": "Oficentro Comercial EPIC",
    "Bldg_BM": "649d3662-2705-4302-91ba-b492750bf5a0",
    "Floor_number": 1,
    "New_Floor_number": 0,
    "Floor_BM": "fb81710b-b101-4270-8d65-98158eb2af40",
    "Area_Code": "B",
    "New_Area_Code": "-",
    "Area_BM": "fb81710b-b101-4270-8d65-98158eb2af40",
    "Seat_ID": 6344,
    "Seat_Code": 12,
    "New_Seat_Code": "2-12",
    "Seat_BM": "da0734d5-1f98-484c-aee2-b243bb4a2c27"
  },
  {
    "Site_name": "Costa Rica",
    "New_Site_name": "San Rafael de Escazu, San José",
    "Site_BM": "2cc5f62b-5b1e-4aac-b6b0-5b98f724927f",
    "Bldg_name": "EPIC",
    "New_Bldg_name": "Oficentro Comercial EPIC",
    "Bldg_BM": "649d3662-2705-4302-91ba-b492750bf5a0",
    "Floor_number": 1,
    "New_Floor_number": 0,
    "Floor_BM": "fb81710b-b101-4270-8d65-98158eb2af40",
    "Area_Code": "B",
    "New_Area_Code": "-",
    "Area_BM": "fb81710b-b101-4270-8d65-98158eb2af40",
    "Seat_ID": 6345,
    "Seat_Code": 13,
    "New_Seat_Code": "2-13",
    "Seat_BM": "717bd337-0d0b-44cf-9a33-6a209ede3c1d"
  }
]